Metadata-Version: 1.0
Name: Salman-distributions
Version: 1.0
Summary: Gaussian and Binomial distributions
Home-page: UNKNOWN
Author: ['Salman Gassem']
Author-email: UNKNOWN
License: UNKNOWN
Platform: UNKNOWN
